hugchat_api/__init__.py
hugchat_api/terminal_cli.py
hugchat_api/core/Bot.py
hugchat_api/core/Chatflow.py
hugchat_api/core/CorotineLoop.py
hugchat_api/core/Customflow.py
hugchat_api/core/Exceptions.py
hugchat_api/core/ListBots.py
hugchat_api/core/Message.py
hugchat_api/core/Sign.py
hugchat_api/core/ThreadPool.py
hugchat_api/core/WebSearch.py
hugchat_api/core/Workflow.py
hugchat_api/core/__init__.py
hugchat_api/core/config.py
hugchat_api/utils/PrintLoop.py
hugchat_api/utils/PrintWeb.py
hugchat_api/utils/Request.py
hugchat_api/utils/__init__.py
hugchat_api-0.0.2.5.dist-info/LICENSE
hugchat_api-0.0.2.5.dist-info/METADATA
hugchat_api-0.0.2.5.dist-info/WHEEL
hugchat_api-0.0.2.5.dist-info/top_level.txt
hugchat_api-0.0.2.5.dist-info/RECORD
