Metadata-Version: 2.1
Name: hugchat-api
Version: 0.0.2.5
Summary: huggingface.co/chat, 'stream' response and 'Search Web' supported. (MetaAI's new model supported)
Home-page: https://github.com/ogios/huggingchat-api
Author: ogios
Author-email: 2134692955@qq.com
License: GNU General Public License v3.0
Project-URL: Wiki, https://github.com/ogios/huggingchat-api/wiki
Classifier: Development Status :: 4 - Beta
Classifier: Intended Audience :: Developers
Classifier: Topic :: Software Development :: Libraries :: Python Modules
Classifier: Programming Language :: Python :: 3
Classifier: Programming Language :: Python :: 3.7
Classifier: Programming Language :: Python :: 3.8
Classifier: Programming Language :: Python :: 3.9
Classifier: Programming Language :: Python :: 3.10
Classifier: Programming Language :: Python :: 3.11
License-File: LICENSE
Requires-Dist: urllib3
Requires-Dist: aiohttp
Requires-Dist: dataclasses-json
Requires-Dist: wcwidth
